google_drive_ocr/__init__.py
google_drive_ocr/application.py
google_drive_ocr/cli.py
google_drive_ocr/errors.py
google_drive_ocr/utils.py
google_drive_ocr-0.2.6.dist-info/AUTHORS.rst
google_drive_ocr-0.2.6.dist-info/LICENSE
google_drive_ocr-0.2.6.dist-info/METADATA
google_drive_ocr-0.2.6.dist-info/WHEEL
google_drive_ocr-0.2.6.dist-info/entry_points.txt
google_drive_ocr-0.2.6.dist-info/top_level.txt
google_drive_ocr-0.2.6.dist-info/RECORD
