Metadata-Version: 2.1
Name: google-drive-ocr
Version: 0.2.6
Summary: Perform OCR using Google's Drive API v3
Home-page: https://github.com/hrishikeshrt/google_drive_ocr
Author: Hrishikesh Terdalkar
Author-email: hrishikeshrt@linuxmail.org
License: GNU General Public License v3
Keywords: google_drive_ocr
Platform: UNKNOWN
Classifier: Development Status :: 4 - Beta
Classifier: Intended Audience :: Developers
Classifier: License :: OSI Approved :: GNU General Public License v3 (GPLv3)
Classifier: Natural Language :: English
Classifier: Topic :: Software Development :: Libraries :: Python Modules
Classifier: Topic :: Software Development :: User Interfaces
Classifier: Topic :: Utilities
Classifier: Programming Language :: Python :: 3
Classifier: Programming Language :: Python :: 3.6
Classifier: Programming Language :: Python :: 3.7
Classifier: Programming Language :: Python :: 3.8
Classifier: Programming Language :: Python :: 3.9
Requires-Python: >=3.6
License-File: LICENSE
License-File: AUTHORS.rst
Requires-Dist: google-api-python-client (>=2.9.0)
Requires-Dist: google-auth-oauthlib (>=0.4.1)
Requires-Dist: tqdm (>=4.60.0)
Requires-Dist: natsort (>=7.0.1)
Requires-Dist: pdf2image (>=1.15.1)
Requires-Dist: ConfigArgParse (>=1.4.1)
